aioqb/__init__.py
aioqb/client.py
aioqb/exceptions.py
aioqb/py.typed
aioqb/typing.py
aioqb/utils.py
aioqb-0.1.6.dist-info/METADATA
aioqb-0.1.6.dist-info/WHEEL
aioqb-0.1.6.dist-info/top_level.txt
aioqb-0.1.6.dist-info/RECORD
