Metadata-Version: 2.1
Name: aioqb
Version: 0.1.6
Summary: Support qbittorrent rpc client and manage server with async/await
Home-page: https://github.com/synodriver/aioqbittorrent
Author: synodriver
Author-email: diguohuangjiajinweijun@gmail.com
Maintainer: v-vinson
License: GPLv3
Project-URL: Bug Tracker, https://github.com/synodriver/aioqbittorrent/issues
Keywords: asyncio,qbittorrent
Classifier: Development Status :: 3 - Alpha
Classifier: Framework :: AsyncIO
Classifier: Operating System :: OS Independent
Classifier: License :: OSI Approved :: GNU General Public License v3 (GPLv3)
Classifier: Programming Language :: Python
Classifier: Programming Language :: Python :: 3.8
Classifier: Programming Language :: Python :: 3.9
Classifier: Programming Language :: Python :: 3.10
Classifier: Programming Language :: Python :: 3.11
Classifier: Programming Language :: Python :: 3.12
Classifier: Programming Language :: Python :: 3.13
Classifier: Programming Language :: Python :: Implementation :: CPython
Requires-Python: >=3.6
Requires-Dist: aiohttp
Requires-Dist: typing-extensions
